shuvel/__init__.py
shuvel/main.py
shuvel/result.py
shuvel/rule.py
shuvel/utils.py
shuvel-0.4.0.dist-info/LICENSE
shuvel-0.4.0.dist-info/METADATA
shuvel-0.4.0.dist-info/WHEEL
shuvel-0.4.0.dist-info/entry_points.txt
shuvel-0.4.0.dist-info/top_level.txt
shuvel-0.4.0.dist-info/RECORD
