Metadata-Version: 2.1
Name: shuvel
Version: 0.4.0
Summary: Unearthing bad code. Performs regex searches, but with more manageable results.
Home-page: https://gitlab.com/TheTwitchy/shuvel
Author: TheTwitchy
Author-email: thetwitchy@thetwitchy.com
License: MIT
Platform: UNKNOWN
Classifier: Development Status :: 2 - Pre-Alpha
Classifier: Topic :: Utilities
Classifier: License :: OSI Approved :: MIT License
License-File: LICENSE
Requires-Dist: click
Requires-Dist: rich
